qwed_open_responses/__init__.py
qwed_open_responses/core.py
qwed_open_responses/guards/__init__.py
qwed_open_responses/guards/argument_guard.py
qwed_open_responses/guards/base.py
qwed_open_responses/guards/math_guard.py
qwed_open_responses/guards/safety_guard.py
qwed_open_responses/guards/schema_guard.py
qwed_open_responses/guards/state_guard.py
qwed_open_responses/guards/tool_guard.py
qwed_open_responses/middleware/__init__.py
qwed_open_responses/middleware/langchain.py
qwed_open_responses/middleware/openai_sdk.py
qwed_open_responses-0.1.0.dist-info/licenses/LICENSE
qwed_open_responses-0.1.0.dist-info/METADATA
qwed_open_responses-0.1.0.dist-info/WHEEL
qwed_open_responses-0.1.0.dist-info/top_level.txt
qwed_open_responses-0.1.0.dist-info/RECORD
