Metadata-Version: 2.4
Name: qwed-open-responses
Version: 0.1.0
Summary: Verification guards for OpenAI Responses API - Verify AI agent outputs before execution
Author-email: QWED-AI <team@qwedai.com>
License:                                  Apache License
Project-URL: Homepage, https://github.com/QWED-AI/qwed-open-responses
Project-URL: Documentation, https://docs.qwedai.com/docs/open-responses
Project-URL: Repository, https://github.com/QWED-AI/qwed-open-responses
Project-URL: Issues, https://github.com/QWED-AI/qwed-open-responses/issues
Keywords: ai,verification,openai,responses-api,agents,tool-calling,structured-outputs,llm,safety
Classifier: Development Status :: 4 - Beta
Classifier: Intended Audience :: Developers
Classifier: License :: OSI Approved :: Apache Software License
Classifier: Operating System :: OS Independent
Classifier: Programming Language :: Python :: 3
Classifier: Programming Language :: Python :: 3.9
Classifier: Programming Language :: Python :: 3.10
Classifier: Programming Language :: Python :: 3.11
Classifier: Programming Language :: Python :: 3.12
Classifier: Topic :: Scientific/Engineering :: Artificial Intelligence
Classifier: Topic :: Software Development :: Libraries :: Python Modules
Requires-Python: >=3.9
License-File: LICENSE
Requires-Dist: jsonschema>=4.17.0
Requires-Dist: pydantic>=2.0.0
Provides-Extra: openai
Requires-Dist: openai>=1.0.0; extra == "openai"
Provides-Extra: langchain
Requires-Dist: langchain>=0.1.0; extra == "langchain"
Requires-Dist: langchain-core>=0.1.0; extra == "langchain"
Provides-Extra: llamaindex
Requires-Dist: llama-index>=0.10.0; extra == "llamaindex"
Provides-Extra: all
Requires-Dist: openai>=1.0.0; extra == "all"
Requires-Dist: langchain>=0.1.0; extra == "all"
Requires-Dist: langchain-core>=0.1.0; extra == "all"
Requires-Dist: llama-index>=0.10.0; extra == "all"
Provides-Extra: dev
Requires-Dist: pytest>=7.0.0; extra == "dev"
Requires-Dist: pytest-asyncio>=0.21.0; extra == "dev"
Requires-Dist: black>=23.0.0; extra == "dev"
Requires-Dist: mypy>=1.0.0; extra == "dev"
Dynamic: license-file
